gsfarc/__init__.py
gsfarc/gptoolbox.py
gsfarc/system.py
gsfarc/esri/toolboxes/GSF.CreateTool.pyt.xml
gsfarc/esri/toolboxes/GSF.pyt
gsfarc/esri/toolboxes/GSF.pyt.xml
gsfarc/gptool/__init__.py
gsfarc/gptool/help.py
gsfarc/gptool/parameter/__init__.py
gsfarc/gptool/parameter/builder.py
gsfarc/gptool/parameter/template.py
gsfarc/gptool/parameter/templates/__init__.py
gsfarc/gptool/parameter/templates/basic.py
gsfarc/gptool/parameter/templates/basicarray.py
gsfarc/gptool/parameter/templates/bool.py
gsfarc/gptool/parameter/templates/boolarray.py
gsfarc/gptool/parameter/templates/boolean.py
gsfarc/gptool/parameter/templates/byte.py
gsfarc/gptool/parameter/templates/bytearray.py
gsfarc/gptool/parameter/templates/double.py
gsfarc/gptool/parameter/templates/doublearray.py
gsfarc/gptool/parameter/templates/enviagcrops.py
gsfarc/gptool/parameter/templates/enviraster.py
gsfarc/gptool/parameter/templates/enviuri.py
gsfarc/gptool/parameter/templates/envivector.py
gsfarc/gptool/parameter/templates/float.py
gsfarc/gptool/parameter/templates/floatarray.py
gsfarc/gptool/parameter/templates/int.py
gsfarc/gptool/parameter/templates/intarray.py
gsfarc/gptool/parameter/templates/long.py
gsfarc/gptool/parameter/templates/long64.py
gsfarc/gptool/parameter/templates/long64array.py
gsfarc/gptool/parameter/templates/longarray.py
gsfarc/gptool/parameter/templates/string.py
gsfarc/gptool/parameter/templates/stringarray.py
gsfarc/gptool/parameter/templates/uint.py
gsfarc/gptool/parameter/templates/uintarray.py
gsfarc/gptool/parameter/templates/ulong.py
gsfarc/gptool/parameter/templates/ulong64.py
gsfarc/gptool/parameter/templates/ulong64array.py
gsfarc/gptool/parameter/templates/ulongarray.py
gsfarc-1.0.4.data/scripts/creategsftoolbox.py
gsfarc-1.0.4.dist-info/DESCRIPTION.rst
gsfarc-1.0.4.dist-info/METADATA
gsfarc-1.0.4.dist-info/RECORD
gsfarc-1.0.4.dist-info/WHEEL
gsfarc-1.0.4.dist-info/metadata.json
gsfarc-1.0.4.dist-info/top_level.txt
